WPP.py
__init__.py
WPP_Papirus-0.0.1.dist-info/LICENSE
WPP_Papirus-0.0.1.dist-info/METADATA
WPP_Papirus-0.0.1.dist-info/WHEEL
WPP_Papirus-0.0.1.dist-info/top_level.txt
WPP_Papirus-0.0.1.dist-info/RECORD
