Metadata-Version: 2.2
Name: WPP_Papirus
Version: 0.0.1
Summary: A Winter Python Package
Author-email: Winter Dev Team <author@example.com>
Project-URL: Homepage, https://github.com/pypa/sampleproject
Project-URL: Issues, https://github.com/pypa/sampleproject/issues
Classifier: Programming Language :: Python :: 3
Classifier: License :: OSI Approved :: MIT License
Classifier: Operating System :: OS Independent
Requires-Python: >=3.8
License-File: LICENSE
